auto_identity/__init__.py
auto_identity/certificate_management.py
auto_identity/certificate_manager.py
auto_identity/key_management.py
auto_identity/registry.py
auto_identity/utils.py
auto_sdk-0.1.6.dist-info/METADATA
auto_sdk-0.1.6.dist-info/WHEEL
auto_sdk-0.1.6.dist-info/top_level.txt
auto_sdk-0.1.6.dist-info/RECORD
