Metadata-Version: 2.1
Name: auto-sdk
Version: 0.1.6
Summary: UNKNOWN
Home-page: https://github.com/subspace/auto-kit
Author: Autonomys
Author-email: jeremy@subspace.network
License: UNKNOWN
Platform: UNKNOWN
Requires-Dist: cryptography <43.0.0,>=42.0.0
Requires-Dist: pyasn1 <0.7.0,>=0.5.0
Requires-Dist: substrate-interface <2.0.0,>=1.7.0
